wolfsoftware/nqueens/__init__.py
wolfsoftware/nqueens/cli.py
wolfsoftware/nqueens/config.py
wolfsoftware/nqueens/exceptions.py
wolfsoftware/nqueens/globals.py
wolfsoftware/nqueens/main.py
wolfsoftware/nqueens/nqueens.py
wolfsoftware.NQueens-0.1.1.dist-info/LICENSE.md
wolfsoftware.NQueens-0.1.1.dist-info/METADATA
wolfsoftware.NQueens-0.1.1.dist-info/WHEEL
wolfsoftware.NQueens-0.1.1.dist-info/entry_points.txt
wolfsoftware.NQueens-0.1.1.dist-info/top_level.txt
wolfsoftware.NQueens-0.1.1.dist-info/RECORD
