Metadata-Version: 2.1
Name: wolfsoftware.NQueens
Version: 0.1.1
Summary: A simple solution for the N Queens problem.
Home-page: https://github.com/TheGrotShop/NQueens-package
Author: Wolf Software
Author-email: pypi@wolfsoftware.com
Project-URL: Source, https://github.com/TheGrotShop/NQueens-package
Project-URL: Tracker, https://github.com/TheGrotShop/NQueens-package/issues/
Project-URL: Documentation, https://github.com/TheGrotShop/NQueens-package
Project-URL: Sponsor, https://github.com/sponsors/WolfSoftware
Classifier: Environment :: Console
Classifier: Intended Audience :: Developers
Classifier: Programming Language :: Python :: 3
Classifier: License :: OSI Approved :: MIT License
Classifier: Operating System :: OS Independent
Classifier: Topic :: Software Development
Requires-Python: >=3.9
License-File: LICENSE.md
Requires-Dist: wolfsoftware.notify ==0.1.0
